printedQrWeb
