Metadata-Version: 1.1
Name: PrintedQrWeb
Version: 0.0.4-2
Summary: PrintedQr Web interface
Home-page: http://printerqr.dlabs.co/
Author: UNKNOWN
Author-email: UNKNOWN
License: GPL2
Download-URL: http://printerqr.dlabs.co
Platform: UNKNOWN
Classifier: Development Status :: 4 - Beta
Requires: PrintedQr
